daffodil/__init__.py
daffodil/daf.py
daffodil/keyedlist.py
daffodil/py.typed
daffodil/lib/__init__.py
daffodil/lib/daf_indexing.py
daffodil/lib/daf_md.py
daffodil/lib/daf_pandas.py
daffodil/lib/daf_pdf.py
daffodil/lib/daf_sql.py
daffodil/lib/daf_types.py
daffodil/lib/daf_utils.py
daffodil/lib/md_demo.py
daffodil-0.5.10.dist-info/METADATA
daffodil-0.5.10.dist-info/WHEEL
daffodil-0.5.10.dist-info/top_level.txt
daffodil-0.5.10.dist-info/RECORD
