Metadata-Version: 2.4
Name: daffodil
Version: 0.5.10
Summary: Daffodil provides lightweight and fast 2-D dataframes
Author-email: Ray Lutz <raylutz@cognisys.com>
License: MIT
Project-URL: Homepage, https://github.com/raylutz/daffodil
Project-URL: Repository, https://github.com/raylutz/daffodil
Project-URL: Issues, https://github.com/raylutz/daffodil/issues
Project-URL: Changelog, https://github.com/raylutz/daffodil/blob/main/CHANGELOG.md
Project-URL: Roadmap, https://github.com/raylutz/daffodil/blob/main/ROADMAP.md
Classifier: Development Status :: 2 - Pre-Alpha
Classifier: Programming Language :: Python :: 3
Classifier: License :: OSI Approved :: MIT License
Classifier: Operating System :: OS Independent
Requires-Python: >=3.6
Requires-Dist: xlsx2csv>=0.8.2
Requires-Dist: Markdown>=3.4.1
Provides-Extra: numpy
Requires-Dist: numpy; extra == "numpy"
